Metadata-Version: 2.1
Name: speewee
Version: 0.0.1
Summary: Upgrade based on official peewee 3.14.0
Home-page: https://github.com/langengel/speewee
Author: langengel
Author-email: langengel@qq.com
License: MIT
Platform: UNKNOWN
Classifier: License :: OSI Approved :: MIT License
Classifier: Natural Language :: English
Classifier: Programming Language :: Python :: 3
Classifier: Operating System :: OS Independent
